{"paths": {"admin/js/vendor/select2/i18n/af.4f6fcd73488c.js": "admin/js/vendor/select2/i18n/af.4f6fcd73488c.b03483e1e9e6.js", "admin/js/vendor/select2/i18n/af.4f6fcd73488c.js.gz": "admin\\js\\vendor\\select2\\i18n\\af.4f6fcd73488c.js.d41d8cd98f00.gz", "admin/js/vendor/select2/i18n/af.js": "admin/js/vendor/select2/i18n/af.d41d8cd98f00.js", "admin/js/vendor/select2/i18n/af.js.gz": "admin\\js\\vendor\\select2\\i18n\\af.js.d41d8cd98f00.gz", "admin/js/vendor/select2/i18n/ar.65aa8e36bf5d.js": "admin/js/vendor/select2/i18n/ar.65aa8e36bf5d.8805cb817f58.js", "admin/js/vendor/select2/i18n/ar.65aa8e36bf5d.js.gz": "admin\\js\\vendor\\select2\\i18n\\ar.65aa8e36bf5d.js.d41d8cd98f00.gz", "admin/js/vendor/select2/i18n/ar.js": "admin/js/vendor/select2/i18n/ar.d41d8cd98f00.js", "admin/js/vendor/select2/i18n/ar.js.gz": "admin\\js\\vendor\\select2\\i18n\\ar.js.d41d8cd98f00.gz", "admin/js/vendor/select2/i18n/az.270c257daf81.js": "admin/js/vendor/select2/i18n/az.270c257daf81.6236c7429891.js", "admin/js/vendor/select2/i18n/az.270c257daf81.js.gz": "admin\\js\\vendor\\select2\\i18n\\az.270c257daf81.js.d41d8cd98f00.gz", "admin/js/vendor/select2/i18n/az.js": "admin/js/vendor/select2/i18n/az.d41d8cd98f00.js", "admin/js/vendor/select2/i18n/az.js.gz": "admin\\js\\vendor\\select2\\i18n\\az.js.d41d8cd98f00.gz", "admin/js/vendor/select2/i18n/bg.39b8be30d4f0.js": "admin/js/vendor/select2/i18n/bg.39b8be30d4f0.2bb639d9db98.js", "admin/js/vendor/select2/i18n/bg.39b8be30d4f0.js.gz": "admin\\js\\vendor\\select2\\i18n\\bg.39b8be30d4f0.js.d41d8cd98f00.gz", "admin/js/vendor/select2/i18n/bg.js": "admin/js/vendor/select2/i18n/bg.d41d8cd98f00.js", "admin/js/vendor/select2/i18n/bg.js.gz": "admin\\js\\vendor\\select2\\i18n\\bg.js.d41d8cd98f00.gz", "admin/js/vendor/select2/i18n/bn.6d42b4dd5665.js": "admin/js/vendor/select2/i18n/bn.6d42b4dd5665.04e3ad3c557a.js", "admin/js/vendor/select2/i18n/bn.6d42b4dd5665.js.gz": "admin\\js\\vendor\\select2\\i18n\\bn.6d42b4dd5665.js.d41d8cd98f00.gz", "admin/js/vendor/select2/i18n/bn.js": "admin/js/vendor/select2/i18n/bn.d41d8cd98f00.js", "admin/js/vendor/select2/i18n/bn.js.gz": "admin\\js\\vendor\\select2\\i18n\\bn.js.d41d8cd98f00.gz", "admin/js/vendor/select2/i18n/bs.91624382358e.js": "admin/js/vendor/select2/i18n/bs.91624382358e.7dcc0f93e7cb.js", "admin/js/vendor/select2/i18n/bs.91624382358e.js.gz": "admin\\js\\vendor\\select2\\i18n\\bs.91624382358e.js.d41d8cd98f00.gz", "admin/js/vendor/select2/i18n/bs.js": "admin/js/vendor/select2/i18n/bs.d41d8cd98f00.js", "admin/js/vendor/select2/i18n/bs.js.gz": "admin\\js\\vendor\\select2\\i18n\\bs.js.d41d8cd98f00.gz", "admin/js/vendor/select2/i18n/ca.a166b745933a.js": "admin/js/vendor/select2/i18n/ca.a166b745933a.2463a5862975.js", "admin/js/vendor/select2/i18n/ca.a166b745933a.js.gz": "admin\\js\\vendor\\select2\\i18n\\ca.a166b745933a.js.d41d8cd98f00.gz", "admin/js/vendor/select2/i18n/ca.js": "admin/js/vendor/select2/i18n/ca.d41d8cd98f00.js", "admin/js/vendor/select2/i18n/ca.js.gz": "admin\\js\\vendor\\select2\\i18n\\ca.js.d41d8cd98f00.gz", "admin/js/vendor/select2/i18n/cs.4f43e8e7d33a.js": "admin/js/vendor/select2/i18n/cs.4f43e8e7d33a.e2d5190024e7.js", "admin/js/vendor/select2/i18n/cs.4f43e8e7d33a.js.gz": "admin\\js\\vendor\\select2\\i18n\\cs.4f43e8e7d33a.js.d41d8cd98f00.gz", "admin/js/vendor/select2/i18n/cs.js": "admin/js/vendor/select2/i18n/cs.d41d8cd98f00.js", "admin/js/vendor/select2/i18n/cs.js.gz": "admin\\js\\vendor\\select2\\i18n\\cs.js.d41d8cd98f00.gz", "admin/js/vendor/select2/i18n/da.766346afe4dd.js": "admin/js/vendor/select2/i18n/da.766346afe4dd.c5b263ee4ba6.js", "admin/js/vendor/select2/i18n/da.766346afe4dd.js.gz": "admin\\js\\vendor\\select2\\i18n\\da.766346afe4dd.js.d41d8cd98f00.gz", "admin/js/vendor/select2/i18n/da.js": "admin/js/vendor/select2/i18n/da.d41d8cd98f00.js", "admin/js/vendor/select2/i18n/da.js.gz": "admin\\js\\vendor\\select2\\i18n\\da.js.d41d8cd98f00.gz", "admin/js/vendor/select2/i18n/de.8a1c222b0204.js": "admin/js/vendor/select2/i18n/de.8a1c222b0204.b6d7419dfbb6.js", "admin/js/vendor/select2/i18n/de.8a1c222b0204.js.gz": "admin\\js\\vendor\\select2\\i18n\\de.8a1c222b0204.js.d41d8cd98f00.gz", "admin/js/vendor/select2/i18n/de.js": "admin/js/vendor/select2/i18n/de.d41d8cd98f00.js", "admin/js/vendor/select2/i18n/de.js.gz": "admin\\js\\vendor\\select2\\i18n\\de.js.d41d8cd98f00.gz", "admin/js/vendor/select2/i18n/dsb.56372c92d2f1.js": "admin/js/vendor/select2/i18n/dsb.56372c92d2f1.b1ab3ffb70cf.js", "admin/js/vendor/select2/i18n/dsb.56372c92d2f1.js.gz": "admin\\js\\vendor\\select2\\i18n\\dsb.56372c92d2f1.js.d41d8cd98f00.gz", "admin/js/vendor/select2/i18n/dsb.js": "admin/js/vendor/select2/i18n/dsb.d41d8cd98f00.js", "admin/js/vendor/select2/i18n/dsb.js.gz": "admin\\js\\vendor\\select2\\i18n\\dsb.js.d41d8cd98f00.gz", "admin/js/vendor/select2/i18n/el.27097f071856.js": "admin/js/vendor/select2/i18n/el.27097f071856.b9449ec9469c.js", "admin/js/vendor/select2/i18n/el.27097f071856.js.gz": "admin\\js\\vendor\\select2\\i18n\\el.27097f071856.js.d41d8cd98f00.gz", "admin/js/vendor/select2/i18n/el.js": "admin/js/vendor/select2/i18n/el.d41d8cd98f00.js", "admin/js/vendor/select2/i18n/el.js.gz": "admin\\js\\vendor\\select2\\i18n\\el.js.d41d8cd98f00.gz", "admin/js/vendor/select2/i18n/en.cf932ba09a98.js": "admin/js/vendor/select2/i18n/en.cf932ba09a98.a736240bea8a.js", "admin/js/vendor/select2/i18n/en.cf932ba09a98.js.gz": "admin\\js\\vendor\\select2\\i18n\\en.cf932ba09a98.js.d41d8cd98f00.gz", "admin/js/vendor/select2/i18n/en.js": "admin/js/vendor/select2/i18n/en.d41d8cd98f00.js", "admin/js/vendor/select2/i18n/en.js.gz": "admin\\js\\vendor\\select2\\i18n\\en.js.d41d8cd98f00.gz", "admin/js/vendor/select2/i18n/es.66dbc2652fb1.js": "admin/js/vendor/select2/i18n/es.66dbc2652fb1.3ae888b7b053.js", "admin/js/vendor/select2/i18n/es.66dbc2652fb1.js.gz": "admin\\js\\vendor\\select2\\i18n\\es.66dbc2652fb1.js.d41d8cd98f00.gz", "admin/js/vendor/select2/i18n/es.js": "admin/js/vendor/select2/i18n/es.d41d8cd98f00.js", "admin/js/vendor/select2/i18n/es.js.gz": "admin\\js\\vendor\\select2\\i18n\\es.js.d41d8cd98f00.gz", "admin/js/vendor/select2/i18n/et.2b96fd98289d.js": "admin/js/vendor/select2/i18n/et.2b96fd98289d.2bd9febda721.js", "admin/js/vendor/select2/i18n/et.2b96fd98289d.js.gz": "admin\\js\\vendor\\select2\\i18n\\et.2b96fd98289d.js.d41d8cd98f00.gz", "admin/js/vendor/select2/i18n/et.js": "admin/js/vendor/select2/i18n/et.d41d8cd98f00.js", "admin/js/vendor/select2/i18n/et.js.gz": "admin\\js\\vendor\\select2\\i18n\\et.js.d41d8cd98f00.gz", "admin/js/vendor/select2/i18n/eu.adfe5c97b72c.js": "admin/js/vendor/select2/i18n/eu.adfe5c97b72c.c43c61d954be.js", "admin/js/vendor/select2/i18n/eu.adfe5c97b72c.js.gz": "admin\\js\\vendor\\select2\\i18n\\eu.adfe5c97b72c.js.d41d8cd98f00.gz", "admin/js/vendor/select2/i18n/eu.js": "admin/js/vendor/select2/i18n/eu.d41d8cd98f00.js", "admin/js/vendor/select2/i18n/eu.js.gz": "admin\\js\\vendor\\select2\\i18n\\eu.js.d41d8cd98f00.gz", "admin/js/vendor/select2/i18n/fa.3b5bd1961cfd.js": "admin/js/vendor/select2/i18n/fa.3b5bd1961cfd.142f247c1211.js", "admin/js/vendor/select2/i18n/fa.3b5bd1961cfd.js.gz": "admin\\js\\vendor\\select2\\i18n\\fa.3b5bd1961cfd.js.d41d8cd98f00.gz", "admin/js/vendor/select2/i18n/fa.js": "admin/js/vendor/select2/i18n/fa.d41d8cd98f00.js", "admin/js/vendor/select2/i18n/fa.js.gz": "admin\\js\\vendor\\select2\\i18n\\fa.js.d41d8cd98f00.gz", "admin/js/vendor/select2/i18n/fi.614ec42aa9ba.js": "admin/js/vendor/select2/i18n/fi.614ec42aa9ba.c40303e39caf.js", "admin/js/vendor/select2/i18n/fi.614ec42aa9ba.js.gz": "admin\\js\\vendor\\select2\\i18n\\fi.614ec42aa9ba.js.d41d8cd98f00.gz", "admin/js/vendor/select2/i18n/fi.js": "admin/js/vendor/select2/i18n/fi.d41d8cd98f00.js", "admin/js/vendor/select2/i18n/fi.js.gz": "admin\\js\\vendor\\select2\\i18n\\fi.js.d41d8cd98f00.gz", "admin/js/vendor/select2/i18n/fr.05e0542fcfe6.js": "admin/js/vendor/select2/i18n/fr.05e0542fcfe6.224a5e4b028d.js", "admin/js/vendor/select2/i18n/fr.05e0542fcfe6.js.gz": "admin\\js\\vendor\\select2\\i18n\\fr.05e0542fcfe6.js.d41d8cd98f00.gz", "admin/js/vendor/select2/i18n/fr.js": "admin/js/vendor/select2/i18n/fr.d41d8cd98f00.js", "admin/js/vendor/select2/i18n/fr.js.gz": "admin\\js\\vendor\\select2\\i18n\\fr.js.d41d8cd98f00.gz", "admin/js/vendor/select2/i18n/gl.d99b1fedaa86.js": "admin/js/vendor/select2/i18n/gl.d99b1fedaa86.0141f0744bab.js", "admin/js/vendor/select2/i18n/gl.d99b1fedaa86.js.gz": "admin\\js\\vendor\\select2\\i18n\\gl.d99b1fedaa86.js.d41d8cd98f00.gz", "admin/js/vendor/select2/i18n/gl.js": "admin/js/vendor/select2/i18n/gl.d41d8cd98f00.js", "admin/js/vendor/select2/i18n/gl.js.gz": "admin\\js\\vendor\\select2\\i18n\\gl.js.d41d8cd98f00.gz", "admin/js/vendor/select2/i18n/he.e420ff6cd3ed.js": "admin/js/vendor/select2/i18n/he.e420ff6cd3ed.828f17d170db.js", "admin/js/vendor/select2/i18n/he.e420ff6cd3ed.js.gz": "admin\\js\\vendor\\select2\\i18n\\he.e420ff6cd3ed.js.d41d8cd98f00.gz", "admin/js/vendor/select2/i18n/he.js": "admin/js/vendor/select2/i18n/he.d41d8cd98f00.js", "admin/js/vendor/select2/i18n/he.js.gz": "admin\\js\\vendor\\select2\\i18n\\he.js.d41d8cd98f00.gz", "admin/js/vendor/select2/i18n/hi.70640d41628f.js": "admin/js/vendor/select2/i18n/hi.70640d41628f.83ba5a2eeae2.js", "admin/js/vendor/select2/i18n/hi.70640d41628f.js.gz": "admin\\js\\vendor\\select2\\i18n\\hi.70640d41628f.js.d41d8cd98f00.gz", "admin/js/vendor/select2/i18n/hi.js": "admin/js/vendor/select2/i18n/hi.d41d8cd98f00.js", "admin/js/vendor/select2/i18n/hi.js.gz": "admin\\js\\vendor\\select2\\i18n\\hi.js.d41d8cd98f00.gz", "admin/js/vendor/select2/i18n/hr.a2b092cc1147.js": "admin/js/vendor/select2/i18n/hr.a2b092cc1147.922b85b38959.js", "admin/js/vendor/select2/i18n/hr.a2b092cc1147.js.gz": "admin\\js\\vendor\\select2\\i18n\\hr.a2b092cc1147.js.d41d8cd98f00.gz", "admin/js/vendor/select2/i18n/hr.js": "admin/js/vendor/select2/i18n/hr.d41d8cd98f00.js", "admin/js/vendor/select2/i18n/hr.js.gz": "admin\\js\\vendor\\select2\\i18n\\hr.js.d41d8cd98f00.gz", "admin/js/vendor/select2/i18n/hsb.fa3b55265efe.js": "admin/js/vendor/select2/i18n/hsb.fa3b55265efe.ad373a5362d5.js", "admin/js/vendor/select2/i18n/hsb.fa3b55265efe.js.gz": "admin\\js\\vendor\\select2\\i18n\\hsb.fa3b55265efe.js.d41d8cd98f00.gz", "admin/js/vendor/select2/i18n/hsb.js": "admin/js/vendor/select2/i18n/hsb.d41d8cd98f00.js", "admin/js/vendor/select2/i18n/hsb.js.gz": "admin\\js\\vendor\\select2\\i18n\\hsb.js.d41d8cd98f00.gz", "admin/js/vendor/select2/i18n/hu.6ec6039cb8a3.js": "admin/js/vendor/select2/i18n/hu.6ec6039cb8a3.e45c27137569.js", "admin/js/vendor/select2/i18n/hu.6ec6039cb8a3.js.gz": "admin\\js\\vendor\\select2\\i18n\\hu.6ec6039cb8a3.js.d41d8cd98f00.gz", "admin/js/vendor/select2/i18n/hu.js": "admin/js/vendor/select2/i18n/hu.d41d8cd98f00.js", "admin/js/vendor/select2/i18n/hu.js.gz": "admin\\js\\vendor\\select2\\i18n\\hu.js.d41d8cd98f00.gz", "admin/js/vendor/select2/i18n/hy.c7babaeef5a6.js": "admin/js/vendor/select2/i18n/hy.c7babaeef5a6.150864ec3413.js", "admin/js/vendor/select2/i18n/hy.c7babaeef5a6.js.gz": "admin\\js\\vendor\\select2\\i18n\\hy.c7babaeef5a6.js.d41d8cd98f00.gz", "admin/js/vendor/select2/i18n/hy.js": "admin/js/vendor/select2/i18n/hy.d41d8cd98f00.js", "admin/js/vendor/select2/i18n/hy.js.gz": "admin\\js\\vendor\\select2\\i18n\\hy.js.d41d8cd98f00.gz", "admin/js/vendor/select2/i18n/id.04debded514d.js": "admin/js/vendor/select2/i18n/id.04debded514d.2e53f749e4d5.js", "admin/js/vendor/select2/i18n/id.04debded514d.js.gz": "admin\\js\\vendor\\select2\\i18n\\id.04debded514d.js.d41d8cd98f00.gz", "admin/js/vendor/select2/i18n/id.js": "admin/js/vendor/select2/i18n/id.d41d8cd98f00.js", "admin/js/vendor/select2/i18n/id.js.gz": "admin\\js\\vendor\\select2\\i18n\\id.js.d41d8cd98f00.gz", "admin/js/vendor/select2/i18n/is.3ddd9a6a97e9.js": "admin/js/vendor/select2/i18n/is.3ddd9a6a97e9.686d32e4d5e6.js", "admin/js/vendor/select2/i18n/is.3ddd9a6a97e9.js.gz": "admin\\js\\vendor\\select2\\i18n\\is.3ddd9a6a97e9.js.d41d8cd98f00.gz", "admin/js/vendor/select2/i18n/is.js": "admin/js/vendor/select2/i18n/is.d41d8cd98f00.js", "admin/js/vendor/select2/i18n/is.js.gz": "admin\\js\\vendor\\select2\\i18n\\is.js.d41d8cd98f00.gz", "admin/js/vendor/select2/i18n/it.be4fe8d365b5.js": "admin/js/vendor/select2/i18n/it.be4fe8d365b5.1b16e89ede3b.js", "admin/js/vendor/select2/i18n/it.be4fe8d365b5.js.gz": "admin\\js\\vendor\\select2\\i18n\\it.be4fe8d365b5.js.d41d8cd98f00.gz", "admin/js/vendor/select2/i18n/it.js": "admin/js/vendor/select2/i18n/it.d41d8cd98f00.js", "admin/js/vendor/select2/i18n/it.js.gz": "admin\\js\\vendor\\select2\\i18n\\it.js.d41d8cd98f00.gz", "admin/js/vendor/select2/i18n/ja.170ae885d74f.js": "admin/js/vendor/select2/i18n/ja.170ae885d74f.b94b9c0e70a3.js", "admin/js/vendor/select2/i18n/ja.170ae885d74f.js.gz": "admin\\js\\vendor\\select2\\i18n\\ja.170ae885d74f.js.d41d8cd98f00.gz", "admin/js/vendor/select2/i18n/ja.js": "admin/js/vendor/select2/i18n/ja.d41d8cd98f00.js", "admin/js/vendor/select2/i18n/ja.js.gz": "admin\\js\\vendor\\select2\\i18n\\ja.js.d41d8cd98f00.gz", "admin/js/vendor/select2/i18n/ka.2083264a54f0.js": "admin/js/vendor/select2/i18n/ka.2083264a54f0.a81569ec3800.js", "admin/js/vendor/select2/i18n/ka.2083264a54f0.js.gz": "admin\\js\\vendor\\select2\\i18n\\ka.2083264a54f0.js.d41d8cd98f00.gz", "admin/js/vendor/select2/i18n/ka.js": "admin/js/vendor/select2/i18n/ka.d41d8cd98f00.js", "admin/js/vendor/select2/i18n/ka.js.gz": "admin\\js\\vendor\\select2\\i18n\\ka.js.d41d8cd98f00.gz", "admin/js/vendor/select2/i18n/km.c23089cb06ca.js": "admin/js/vendor/select2/i18n/km.c23089cb06ca.53fed178211e.js", "admin/js/vendor/select2/i18n/km.c23089cb06ca.js.gz": "admin\\js\\vendor\\select2\\i18n\\km.c23089cb06ca.js.d41d8cd98f00.gz", "admin/js/vendor/select2/i18n/km.js": "admin/js/vendor/select2/i18n/km.d41d8cd98f00.js", "admin/js/vendor/select2/i18n/km.js.gz": "admin\\js\\vendor\\select2\\i18n\\km.js.d41d8cd98f00.gz", "admin/js/vendor/select2/i18n/ko.e7be6c20e673.js": "admin/js/vendor/select2/i18n/ko.e7be6c20e673.703f3ba62f25.js", "admin/js/vendor/select2/i18n/ko.e7be6c20e673.js.gz": "admin\\js\\vendor\\select2\\i18n\\ko.e7be6c20e673.js.d41d8cd98f00.gz", "admin/js/vendor/select2/i18n/ko.js": "admin/js/vendor/select2/i18n/ko.d41d8cd98f00.js", "admin/js/vendor/select2/i18n/ko.js.gz": "admin\\js\\vendor\\select2\\i18n\\ko.js.d41d8cd98f00.gz", "admin/js/vendor/select2/i18n/lt.23c7ce903300.js": "admin/js/vendor/select2/i18n/lt.23c7ce903300.23264ff51adc.js", "admin/js/vendor/select2/i18n/lt.23c7ce903300.js.gz": "admin\\js\\vendor\\select2\\i18n\\lt.23c7ce903300.js.d41d8cd98f00.gz", "admin/js/vendor/select2/i18n/lt.js": "admin/js/vendor/select2/i18n/lt.d41d8cd98f00.js", "admin/js/vendor/select2/i18n/lt.js.gz": "admin\\js\\vendor\\select2\\i18n\\lt.js.d41d8cd98f00.gz", "admin/js/vendor/select2/i18n/lv.08e62128eac1.js": "admin/js/vendor/select2/i18n/lv.08e62128eac1.5e32e4139043.js", "admin/js/vendor/select2/i18n/lv.08e62128eac1.js.gz": "admin\\js\\vendor\\select2\\i18n\\lv.08e62128eac1.js.d41d8cd98f00.gz", "admin/js/vendor/select2/i18n/lv.js": "admin/js/vendor/select2/i18n/lv.d41d8cd98f00.js", "admin/js/vendor/select2/i18n/lv.js.gz": "admin\\js\\vendor\\select2\\i18n\\lv.js.d41d8cd98f00.gz", "admin/js/vendor/select2/i18n/mk.dabbb9087130.js": "admin/js/vendor/select2/i18n/mk.dabbb9087130.465bc25ef379.js", "admin/js/vendor/select2/i18n/mk.dabbb9087130.js.gz": "admin\\js\\vendor\\select2\\i18n\\mk.dabbb9087130.js.d41d8cd98f00.gz", "admin/js/vendor/select2/i18n/mk.js": "admin/js/vendor/select2/i18n/mk.d41d8cd98f00.js", "admin/js/vendor/select2/i18n/mk.js.gz": "admin\\js\\vendor\\select2\\i18n\\mk.js.d41d8cd98f00.gz", "admin/js/vendor/select2/i18n/ms.4ba82c9a51ce.js": "admin/js/vendor/select2/i18n/ms.4ba82c9a51ce.3c136724820b.js", "admin/js/vendor/select2/i18n/ms.4ba82c9a51ce.js.gz": "admin\\js\\vendor\\select2\\i18n\\ms.4ba82c9a51ce.js.d41d8cd98f00.gz", "admin/js/vendor/select2/i18n/ms.js": "admin/js/vendor/select2/i18n/ms.d41d8cd98f00.js", "admin/js/vendor/select2/i18n/ms.js.gz": "admin\\js\\vendor\\select2\\i18n\\ms.js.d41d8cd98f00.gz", "admin/js/vendor/select2/i18n/nb.da2fce143f27.js": "admin/js/vendor/select2/i18n/nb.da2fce143f27.e08b1d6c871c.js", "admin/js/vendor/select2/i18n/nb.da2fce143f27.js.gz": "admin\\js\\vendor\\select2\\i18n\\nb.da2fce143f27.js.d41d8cd98f00.gz", "admin/js/vendor/select2/i18n/nb.js": "admin/js/vendor/select2/i18n/nb.d41d8cd98f00.js", "admin/js/vendor/select2/i18n/nb.js.gz": "admin\\js\\vendor\\select2\\i18n\\nb.js.d41d8cd98f00.gz", "admin/js/vendor/select2/i18n/ne.3d79fd3f08db.js": "admin/js/vendor/select2/i18n/ne.3d79fd3f08db.a42f5beff9ec.js", "admin/js/vendor/select2/i18n/ne.3d79fd3f08db.js.gz": "admin\\js\\vendor\\select2\\i18n\\ne.3d79fd3f08db.js.d41d8cd98f00.gz", "admin/js/vendor/select2/i18n/ne.js": "admin/js/vendor/select2/i18n/ne.d41d8cd98f00.js", "admin/js/vendor/select2/i18n/ne.js.gz": "admin\\js\\vendor\\select2\\i18n\\ne.js.d41d8cd98f00.gz", "admin/js/vendor/select2/i18n/nl.997868a37ed8.js": "admin/js/vendor/select2/i18n/nl.997868a37ed8.8cbdab7e04f7.js", "admin/js/vendor/select2/i18n/nl.997868a37ed8.js.gz": "admin\\js\\vendor\\select2\\i18n\\nl.997868a37ed8.js.d41d8cd98f00.gz", "admin/js/vendor/select2/i18n/nl.js": "admin/js/vendor/select2/i18n/nl.d41d8cd98f00.js", "admin/js/vendor/select2/i18n/nl.js.gz": "admin\\js\\vendor\\select2\\i18n\\nl.js.d41d8cd98f00.gz", "admin/js/vendor/select2/i18n/pl.6031b4f16452.js": "admin/js/vendor/select2/i18n/pl.6031b4f16452.f4f4faf127a4.js", "admin/js/vendor/select2/i18n/pl.6031b4f16452.js.gz": "admin\\js\\vendor\\select2\\i18n\\pl.6031b4f16452.js.d41d8cd98f00.gz", "admin/js/vendor/select2/i18n/pl.js": "admin/js/vendor/select2/i18n/pl.d41d8cd98f00.js", "admin/js/vendor/select2/i18n/pl.js.gz": "admin\\js\\vendor\\select2\\i18n\\pl.js.d41d8cd98f00.gz", "admin/js/vendor/select2/i18n/ps.38dfa47af9e0.js": "admin/js/vendor/select2/i18n/ps.38dfa47af9e0.c86fab96d81e.js", "admin/js/vendor/select2/i18n/ps.38dfa47af9e0.js.gz": "admin\\js\\vendor\\select2\\i18n\\ps.38dfa47af9e0.js.d41d8cd98f00.gz", "admin/js/vendor/select2/i18n/ps.js": "admin/js/vendor/select2/i18n/ps.d41d8cd98f00.js", "admin/js/vendor/select2/i18n/ps.js.gz": "admin\\js\\vendor\\select2\\i18n\\ps.js.d41d8cd98f00.gz", "admin/js/vendor/select2/i18n/pt-BR.e1b294433e7f.js": "admin/js/vendor/select2/i18n/pt-BR.e1b294433e7f.d41d8cd98f00.js", "admin/js/vendor/select2/i18n/pt-BR.e1b294433e7f.js.gz": "admin\\js\\vendor\\select2\\i18n\\pt-BR.e1b294433e7f.js.d41d8cd98f00.gz", "admin/js/vendor/select2/i18n/pt-BR.js": "admin/js/vendor/select2/i18n/pt-BR.d41d8cd98f00.js", "admin/js/vendor/select2/i18n/pt-BR.js.gz": "admin\\js\\vendor\\select2\\i18n\\pt-BR.js.d41d8cd98f00.gz", "admin/js/vendor/select2/i18n/pt.33b4a3b44d43.js": "admin/js/vendor/select2/i18n/pt.33b4a3b44d43.1fad42b6e5ee.js", "admin/js/vendor/select2/i18n/pt.33b4a3b44d43.js.gz": "admin\\js\\vendor\\select2\\i18n\\pt.33b4a3b44d43.js.d41d8cd98f00.gz", "admin/js/vendor/select2/i18n/pt.js": "admin/js/vendor/select2/i18n/pt.d41d8cd98f00.js", "admin/js/vendor/select2/i18n/pt.js.gz": "admin\\js\\vendor\\select2\\i18n\\pt.js.d41d8cd98f00.gz", "admin/js/vendor/select2/i18n/ro.f75cb460ec3b.js": "admin/js/vendor/select2/i18n/ro.f75cb460ec3b.d41d8cd98f00.js", "admin/js/vendor/select2/i18n/ro.f75cb460ec3b.js.gz": "admin\\js\\vendor\\select2\\i18n\\ro.f75cb460ec3b.js.d41d8cd98f00.gz", "admin/js/vendor/select2/i18n/ro.js": "admin/js/vendor/select2/i18n/ro.d41d8cd98f00.js", "admin/js/vendor/select2/i18n/ro.js.gz": "admin\\js\\vendor\\select2\\i18n\\ro.js.d41d8cd98f00.gz", "admin/js/vendor/select2/i18n/ru.934aa95f5b5f.js": "admin/js/vendor/select2/i18n/ru.934aa95f5b5f.d41d8cd98f00.js", "admin/js/vendor/select2/i18n/ru.934aa95f5b5f.js.gz": "admin\\js\\vendor\\select2\\i18n\\ru.934aa95f5b5f.js.d41d8cd98f00.gz", "admin/js/vendor/select2/i18n/ru.js": "admin/js/vendor/select2/i18n/ru.d41d8cd98f00.js", "admin/js/vendor/select2/i18n/ru.js.gz": "admin\\js\\vendor\\select2\\i18n\\ru.js.d41d8cd98f00.gz", "admin/js/vendor/select2/i18n/sk.33d02cef8d11.js": "admin/js/vendor/select2/i18n/sk.33d02cef8d11.d41d8cd98f00.js", "admin/js/vendor/select2/i18n/sk.33d02cef8d11.js.gz": "admin\\js\\vendor\\select2\\i18n\\sk.33d02cef8d11.js.d41d8cd98f00.gz", "admin/js/vendor/select2/i18n/sk.js": "admin/js/vendor/select2/i18n/sk.d41d8cd98f00.js", "admin/js/vendor/select2/i18n/sk.js.gz": "admin\\js\\vendor\\select2\\i18n\\sk.js.d41d8cd98f00.gz", "admin/js/vendor/select2/i18n/sl.131a78bc0752.js": "admin/js/vendor/select2/i18n/sl.131a78bc0752.d41d8cd98f00.js", "admin/js/vendor/select2/i18n/sl.131a78bc0752.js.gz": "admin\\js\\vendor\\select2\\i18n\\sl.131a78bc0752.js.d41d8cd98f00.gz", "admin/js/vendor/select2/i18n/sl.js": "admin/js/vendor/select2/i18n/sl.d41d8cd98f00.js", "admin/js/vendor/select2/i18n/sl.js.gz": "admin\\js\\vendor\\select2\\i18n\\sl.js.d41d8cd98f00.gz", "admin/js/vendor/select2/i18n/sq.5636b60d29c9.js": "admin/js/vendor/select2/i18n/sq.5636b60d29c9.d41d8cd98f00.js", "admin/js/vendor/select2/i18n/sq.5636b60d29c9.js.gz": "admin\\js\\vendor\\select2\\i18n\\sq.5636b60d29c9.js.d41d8cd98f00.gz", "admin/js/vendor/select2/i18n/sq.js": "admin/js/vendor/select2/i18n/sq.d41d8cd98f00.js", "admin/js/vendor/select2/i18n/sq.js.gz": "admin\\js\\vendor\\select2\\i18n\\sq.js.d41d8cd98f00.gz", "admin/js/vendor/select2/i18n/sr-Cyrl.f254bb8c4c7c.js": "admin/js/vendor/select2/i18n/sr-Cyrl.f254bb8c4c7c.d41d8cd98f00.js", "admin/js/vendor/select2/i18n/sr-Cyrl.f254bb8c4c7c.js.gz": "admin\\js\\vendor\\select2\\i18n\\sr-Cyrl.f254bb8c4c7c.js.d41d8cd98f00.gz", "admin/js/vendor/select2/i18n/sr-Cyrl.js": "admin/js/vendor/select2/i18n/sr-Cyrl.d41d8cd98f00.js", "admin/js/vendor/select2/i18n/sr-Cyrl.js.gz": "admin\\js\\vendor\\select2\\i18n\\sr-Cyrl.js.d41d8cd98f00.gz", "admin/js/vendor/select2/i18n/sr.5ed85a48f483.js": "admin/js/vendor/select2/i18n/sr.5ed85a48f483.d41d8cd98f00.js", "admin/js/vendor/select2/i18n/sr.5ed85a48f483.js.gz": "admin\\js\\vendor\\select2\\i18n\\sr.5ed85a48f483.js.d41d8cd98f00.gz", "admin/js/vendor/select2/i18n/sr.js": "admin/js/vendor/select2/i18n/sr.d41d8cd98f00.js", "admin/js/vendor/select2/i18n/sr.js.gz": "admin\\js\\vendor\\select2\\i18n\\sr.js.d41d8cd98f00.gz", "admin/js/vendor/select2/i18n/sv.7a9c2f71e777.js": "admin/js/vendor/select2/i18n/sv.7a9c2f71e777.d41d8cd98f00.js", "admin/js/vendor/select2/i18n/sv.7a9c2f71e777.js.gz": "admin\\js\\vendor\\select2\\i18n\\sv.7a9c2f71e777.js.d41d8cd98f00.gz", "admin/js/vendor/select2/i18n/sv.js": "admin/js/vendor/select2/i18n/sv.d41d8cd98f00.js", "admin/js/vendor/select2/i18n/sv.js.gz": "admin\\js\\vendor\\select2\\i18n\\sv.js.d41d8cd98f00.gz", "admin/js/vendor/select2/i18n/th.f38c20b0221b.js": "admin/js/vendor/select2/i18n/th.f38c20b0221b.d41d8cd98f00.js", "admin/js/vendor/select2/i18n/th.f38c20b0221b.js.gz": "admin\\js\\vendor\\select2\\i18n\\th.f38c20b0221b.js.d41d8cd98f00.gz", "admin/js/vendor/select2/i18n/th.js": "admin/js/vendor/select2/i18n/th.d41d8cd98f00.js", "admin/js/vendor/select2/i18n/th.js.gz": "admin\\js\\vendor\\select2\\i18n\\th.js.d41d8cd98f00.gz", "admin/js/vendor/select2/i18n/tk.7c572a68c78f.js": "admin/js/vendor/select2/i18n/tk.7c572a68c78f.d41d8cd98f00.js", "admin/js/vendor/select2/i18n/tk.7c572a68c78f.js.gz": "admin\\js\\vendor\\select2\\i18n\\tk.7c572a68c78f.js.d41d8cd98f00.gz", "admin/js/vendor/select2/i18n/tk.js": "admin/js/vendor/select2/i18n/tk.d41d8cd98f00.js", "admin/js/vendor/select2/i18n/tk.js.gz": "admin\\js\\vendor\\select2\\i18n\\tk.js.d41d8cd98f00.gz", "admin/js/vendor/select2/i18n/tr.b5a0643d1545.js": "admin/js/vendor/select2/i18n/tr.b5a0643d1545.d41d8cd98f00.js", "admin/js/vendor/select2/i18n/tr.b5a0643d1545.js.gz": "admin\\js\\vendor\\select2\\i18n\\tr.b5a0643d1545.js.d41d8cd98f00.gz", "admin/js/vendor/select2/i18n/tr.js": "admin/js/vendor/select2/i18n/tr.d41d8cd98f00.js", "admin/js/vendor/select2/i18n/tr.js.gz": "admin\\js\\vendor\\select2\\i18n\\tr.js.d41d8cd98f00.gz", "admin/js/vendor/select2/i18n/uk.8cede7f4803c.js": "admin/js/vendor/select2/i18n/uk.8cede7f4803c.d41d8cd98f00.js", "admin/js/vendor/select2/i18n/uk.8cede7f4803c.js.gz": "admin\\js\\vendor\\select2\\i18n\\uk.8cede7f4803c.js.d41d8cd98f00.gz", "admin/js/vendor/select2/i18n/uk.js": "admin/js/vendor/select2/i18n/uk.d41d8cd98f00.js", "admin/js/vendor/select2/i18n/uk.js.gz": "admin\\js\\vendor\\select2\\i18n\\uk.js.d41d8cd98f00.gz", "admin/js/vendor/select2/i18n/vi.097a5b75b3e1.js": "admin/js/vendor/select2/i18n/vi.097a5b75b3e1.d41d8cd98f00.js", "admin/js/vendor/select2/i18n/vi.097a5b75b3e1.js.gz": "admin\\js\\vendor\\select2\\i18n\\vi.097a5b75b3e1.js.d41d8cd98f00.gz", "admin/js/vendor/select2/i18n/vi.js": "admin/js/vendor/select2/i18n/vi.d41d8cd98f00.js", "admin/js/vendor/select2/i18n/vi.js.gz": "admin\\js\\vendor\\select2\\i18n\\vi.js.d41d8cd98f00.gz", "admin/js/vendor/select2/i18n/zh-CN.2cff662ec5f9.js": "admin/js/vendor/select2/i18n/zh-CN.2cff662ec5f9.d41d8cd98f00.js", "admin/js/vendor/select2/i18n/zh-CN.2cff662ec5f9.js.gz": "admin\\js\\vendor\\select2\\i18n\\zh-CN.2cff662ec5f9.js.d41d8cd98f00.gz", "admin/js/vendor/select2/i18n/zh-CN.js": "admin/js/vendor/select2/i18n/zh-CN.d41d8cd98f00.js", "admin/js/vendor/select2/i18n/zh-CN.js.gz": "admin\\js\\vendor\\select2\\i18n\\zh-CN.js.d41d8cd98f00.gz", "admin/js/vendor/select2/i18n/zh-TW.04554a227c2b.js": "admin/js/vendor/select2/i18n/zh-TW.04554a227c2b.d41d8cd98f00.js", "admin/js/vendor/select2/i18n/zh-TW.04554a227c2b.js.gz": "admin\\js\\vendor\\select2\\i18n\\zh-TW.04554a227c2b.js.d41d8cd98f00.gz", "admin/js/vendor/select2/i18n/zh-TW.js": "admin/js/vendor/select2/i18n/zh-TW.d41d8cd98f00.js", "admin/js/vendor/select2/i18n/zh-TW.js.gz": "admin\\js\\vendor\\select2\\i18n\\zh-TW.js.d41d8cd98f00.gz", "admin/css/vendor/select2/LICENSE-SELECT2.f94142512c91.md": "admin\\css\\vendor\\select2\\LICENSE-SELECT2.f94142512c91.d41d8cd98f00.md", "admin/css/vendor/select2/LICENSE-SELECT2.f94142512c91.md.gz": "admin\\css\\vendor\\select2\\LICENSE-SELECT2.f94142512c91.md.d41d8cd98f00.gz", "admin/css/vendor/select2/LICENSE-SELECT2.md": "admin\\css\\vendor\\select2\\LICENSE-SELECT2.d41d8cd98f00.md", "admin/css/vendor/select2/LICENSE-SELECT2.md.gz": "admin\\css\\vendor\\select2\\LICENSE-SELECT2.md.d41d8cd98f00.gz", "admin/css/vendor/select2/select2.a2194c262648.css": "admin/css/vendor/select2/select2.a2194c262648.d41d8cd98f00.css", "admin/css/vendor/select2/select2.a2194c262648.css.gz": "admin\\css\\vendor\\select2\\select2.a2194c262648.css.d41d8cd98f00.gz", "admin/css/vendor/select2/select2.css": "admin/css/vendor/select2/select2.d41d8cd98f00.css", "admin/css/vendor/select2/select2.css.gz": "admin\\css\\vendor\\select2\\select2.css.d41d8cd98f00.gz", "admin/css/vendor/select2/select2.min.9f54e6414f87.css": "admin/css/vendor/select2/select2.min.9f54e6414f87.d41d8cd98f00.css", "admin/css/vendor/select2/select2.min.9f54e6414f87.css.gz": "admin\\css\\vendor\\select2\\select2.min.9f54e6414f87.css.d41d8cd98f00.gz", "admin/css/vendor/select2/select2.min.css": "admin/css/vendor/select2/select2.min.d41d8cd98f00.css", "admin/css/vendor/select2/select2.min.css.gz": "admin\\css\\vendor\\select2\\select2.min.css.d41d8cd98f00.gz", "admin/js/vendor/jquery/jquery.12e87d2f3a4c.js": "admin/js/vendor/jquery/jquery.12e87d2f3a4c.c189afb5631e.js", "admin/js/vendor/jquery/jquery.12e87d2f3a4c.js.gz": "admin\\js\\vendor\\jquery\\jquery.12e87d2f3a4c.js.d41d8cd98f00.gz", "admin/js/vendor/jquery/jquery.js": "admin/js/vendor/jquery/jquery.d41d8cd98f00.js", "admin/js/vendor/jquery/jquery.js.gz": "admin\\js\\vendor\\jquery\\jquery.js.d41d8cd98f00.gz", "admin/js/vendor/jquery/jquery.min.2c872dbe60f4.js": "admin/js/vendor/jquery/jquery.min.2c872dbe60f4.d41d8cd98f00.js", "admin/js/vendor/jquery/jquery.min.2c872dbe60f4.js.gz": "admin\\js\\vendor\\jquery\\jquery.min.2c872dbe60f4.js.d41d8cd98f00.gz", "admin/js/vendor/jquery/jquery.min.js": "admin/js/vendor/jquery/jquery.min.d41d8cd98f00.js", "admin/js/vendor/jquery/jquery.min.js.gz": "admin\\js\\vendor\\jquery\\jquery.min.js.d41d8cd98f00.gz", "admin/js/vendor/jquery/LICENSE.de877aa6d744.txt": "admin\\js\\vendor\\jquery\\LICENSE.de877aa6d744.d41d8cd98f00.txt", "admin/js/vendor/jquery/LICENSE.de877aa6d744.txt.gz": "admin\\js\\vendor\\jquery\\LICENSE.de877aa6d744.txt.d41d8cd98f00.gz", "admin/js/vendor/jquery/LICENSE.txt": "admin\\js\\vendor\\jquery\\LICENSE.d41d8cd98f00.txt", "admin/js/vendor/jquery/LICENSE.txt.gz": "admin\\js\\vendor\\jquery\\LICENSE.txt.d41d8cd98f00.gz", "admin/js/vendor/select2/LICENSE.f94142512c91.md": "admin\\js\\vendor\\select2\\LICENSE.f94142512c91.d41d8cd98f00.md", "admin/js/vendor/select2/LICENSE.f94142512c91.md.gz": "admin\\js\\vendor\\select2\\LICENSE.f94142512c91.md.d41d8cd98f00.gz", "admin/js/vendor/select2/LICENSE.md": "admin\\js\\vendor\\select2\\LICENSE.d41d8cd98f00.md", "admin/js/vendor/select2/LICENSE.md.gz": "admin\\js\\vendor\\select2\\LICENSE.md.d41d8cd98f00.gz", "admin/js/vendor/select2/select2.full.c2afdeda3058.js": "admin/js/vendor/select2/select2.full.c2afdeda3058.d41d8cd98f00.js", "admin/js/vendor/select2/select2.full.c2afdeda3058.js.gz": "admin\\js\\vendor\\select2\\select2.full.c2afdeda3058.js.d41d8cd98f00.gz", "admin/js/vendor/select2/select2.full.js": "admin/js/vendor/select2/select2.full.d41d8cd98f00.js", "admin/js/vendor/select2/select2.full.js.gz": "admin\\js\\vendor\\select2\\select2.full.js.d41d8cd98f00.gz", "admin/js/vendor/select2/select2.full.min.fcd7500d8e13.js": "admin/js/vendor/select2/select2.full.min.fcd7500d8e13.d41d8cd98f00.js", "admin/js/vendor/select2/select2.full.min.fcd7500d8e13.js.gz": "admin\\js\\vendor\\select2\\select2.full.min.fcd7500d8e13.js.d41d8cd98f00.gz", "admin/js/vendor/select2/select2.full.min.js": "admin/js/vendor/select2/select2.full.min.d41d8cd98f00.js", "admin/js/vendor/select2/select2.full.min.js.gz": "admin\\js\\vendor\\select2\\select2.full.min.js.d41d8cd98f00.gz", "admin/js/vendor/xregexp/LICENSE.b6fd2ceea8d3.txt": "admin\\js\\vendor\\xregexp\\LICENSE.b6fd2ceea8d3.d41d8cd98f00.txt", "admin/js/vendor/xregexp/LICENSE.b6fd2ceea8d3.txt.gz": "admin\\js\\vendor\\xregexp\\LICENSE.b6fd2ceea8d3.txt.d41d8cd98f00.gz", "admin/js/vendor/xregexp/LICENSE.txt": "admin\\js\\vendor\\xregexp\\LICENSE.d41d8cd98f00.txt", "admin/js/vendor/xregexp/LICENSE.txt.gz": "admin\\js\\vendor\\xregexp\\LICENSE.txt.d41d8cd98f00.gz", "admin/js/vendor/xregexp/xregexp.a7e08b0ce686.js": "admin/js/vendor/xregexp/xregexp.a7e08b0ce686.d41d8cd98f00.js", "admin/js/vendor/xregexp/xregexp.a7e08b0ce686.js.gz": "admin\\js\\vendor\\xregexp\\xregexp.a7e08b0ce686.js.d41d8cd98f00.gz", "admin/js/vendor/xregexp/xregexp.js": "admin/js/vendor/xregexp/xregexp.d41d8cd98f00.js", "admin/js/vendor/xregexp/xregexp.js.gz": "admin\\js\\vendor\\xregexp\\xregexp.js.d41d8cd98f00.gz", "admin/js/vendor/xregexp/xregexp.min.f1ae4617847c.js": "admin/js/vendor/xregexp/xregexp.min.f1ae4617847c.d41d8cd98f00.js", "admin/js/vendor/xregexp/xregexp.min.f1ae4617847c.js.gz": "admin\\js\\vendor\\xregexp\\xregexp.min.f1ae4617847c.js.d41d8cd98f00.gz", "admin/js/vendor/xregexp/xregexp.min.js": "admin/js/vendor/xregexp/xregexp.min.d41d8cd98f00.js", "admin/js/vendor/xregexp/xregexp.min.js.gz": "admin\\js\\vendor\\xregexp\\xregexp.min.js.d41d8cd98f00.gz", "admin/img/gis/move_vertex_off.7a23bf31ef8a.svg": "admin\\img\\gis\\move_vertex_off.7a23bf31ef8a.d41d8cd98f00.svg", "admin/img/gis/move_vertex_off.7a23bf31ef8a.svg.gz": "admin\\img\\gis\\move_vertex_off.7a23bf31ef8a.svg.d41d8cd98f00.gz", "admin/img/gis/move_vertex_off.svg": "admin\\img\\gis\\move_vertex_off.d41d8cd98f00.svg", "admin/img/gis/move_vertex_off.svg.gz": "admin\\img\\gis\\move_vertex_off.svg.d41d8cd98f00.gz", "admin/img/gis/move_vertex_on.0047eba25b67.svg": "admin\\img\\gis\\move_vertex_on.0047eba25b67.d41d8cd98f00.svg", "admin/img/gis/move_vertex_on.0047eba25b67.svg.gz": "admin\\img\\gis\\move_vertex_on.0047eba25b67.svg.d41d8cd98f00.gz", "admin/img/gis/move_vertex_on.svg": "admin\\img\\gis\\move_vertex_on.d41d8cd98f00.svg", "admin/img/gis/move_vertex_on.svg.gz": "admin\\img\\gis\\move_vertex_on.svg.d41d8cd98f00.gz", "admin/js/admin/DateTimeShortcuts.9f6e209cebca.js": "admin/js/admin/DateTimeShortcuts.9f6e209cebca.9d8651603da6.js", "admin/js/admin/DateTimeShortcuts.9f6e209cebca.js.gz": "admin\\js\\admin\\DateTimeShortcuts.9f6e209cebca.js.d41d8cd98f00.gz", "admin/js/admin/DateTimeShortcuts.js": "admin/js/admin/DateTimeShortcuts.d41d8cd98f00.js", "admin/js/admin/DateTimeShortcuts.js.gz": "admin\\js\\admin\\DateTimeShortcuts.js.d41d8cd98f00.gz", "admin/js/admin/RelatedObjectLookups.ef211845e458.js": "admin/js/admin/RelatedObjectLookups.ef211845e458.d41d8cd98f00.js", "admin/js/admin/RelatedObjectLookups.ef211845e458.js.gz": "admin\\js\\admin\\RelatedObjectLookups.ef211845e458.js.d41d8cd98f00.gz", "admin/js/admin/RelatedObjectLookups.js": "admin/js/admin/RelatedObjectLookups.d41d8cd98f00.js", "admin/js/admin/RelatedObjectLookups.js.gz": "admin\\js\\admin\\RelatedObjectLookups.js.d41d8cd98f00.gz", "admin/css/autocomplete.4a81fc4242d0.css": "admin/css/autocomplete.4a81fc4242d0.d41d8cd98f00.css", "admin/css/autocomplete.4a81fc4242d0.css.gz": "admin\\css\\autocomplete.4a81fc4242d0.css.d41d8cd98f00.gz", "admin/css/autocomplete.css": "admin/css/autocomplete.d41d8cd98f00.css", "admin/css/autocomplete.css.gz": "admin\\css\\autocomplete.css.d41d8cd98f00.gz", "admin/css/base.9f65b5cd54b3.css": "admin/css/base.9f65b5cd54b3.d41d8cd98f00.css", "admin/css/base.9f65b5cd54b3.css.gz": "admin\\css\\base.9f65b5cd54b3.css.d41d8cd98f00.gz", "admin/css/base.css": "admin/css/base.d41d8cd98f00.css", "admin/css/base.css.gz": "admin\\css\\base.css.d41d8cd98f00.gz", "admin/css/changelists.47cb433b29d4.css": "admin/css/changelists.47cb433b29d4.d41d8cd98f00.css", "admin/css/changelists.47cb433b29d4.css.gz": "admin\\css\\changelists.47cb433b29d4.css.d41d8cd98f00.gz", "admin/css/changelists.css": "admin/css/changelists.d41d8cd98f00.css", "admin/css/changelists.css.gz": "admin\\css\\changelists.css.d41d8cd98f00.gz", "admin/css/dark_mode.css": "admin/css/dark_mode.d41d8cd98f00.css", "admin/css/dark_mode.css.gz": "admin\\css\\dark_mode.css.d41d8cd98f00.gz", "admin/css/dark_mode.e18e9a052429.css": "admin/css/dark_mode.e18e9a052429.d41d8cd98f00.css", "admin/css/dark_mode.e18e9a052429.css.gz": "admin\\css\\dark_mode.e18e9a052429.css.d41d8cd98f00.gz", "admin/css/dashboard.css": "admin/css/dashboard.d41d8cd98f00.css", "admin/css/dashboard.css.gz": "admin\\css\\dashboard.css.d41d8cd98f00.gz", "admin/css/dashboard.e90f2068217b.css": "admin/css/dashboard.e90f2068217b.d41d8cd98f00.css", "admin/css/dashboard.e90f2068217b.css.gz": "admin\\css\\dashboard.e90f2068217b.css.d41d8cd98f00.gz", "admin/css/forms.b29a0c8c9155.css": "admin/css/forms.b29a0c8c9155.d41d8cd98f00.css", "admin/css/forms.b29a0c8c9155.css.gz": "admin\\css\\forms.b29a0c8c9155.css.d41d8cd98f00.gz", "admin/css/forms.css": "admin/css/forms.d41d8cd98f00.css", "admin/css/forms.css.gz": "admin\\css\\forms.css.d41d8cd98f00.gz", "admin/css/login.586129c60a93.css": "admin/css/login.586129c60a93.d41d8cd98f00.css", "admin/css/login.586129c60a93.css.gz": "admin\\css\\login.586129c60a93.css.d41d8cd98f00.gz", "admin/css/login.css": "admin/css/login.d41d8cd98f00.css", "admin/css/login.css.gz": "admin\\css\\login.css.d41d8cd98f00.gz", "admin/css/nav_sidebar.css": "admin/css/nav_sidebar.d41d8cd98f00.css", "admin/css/nav_sidebar.css.gz": "admin\\css\\nav_sidebar.css.d41d8cd98f00.gz", "admin/css/nav_sidebar.dd925738f4cc.css": "admin/css/nav_sidebar.dd925738f4cc.d41d8cd98f00.css", "admin/css/nav_sidebar.dd925738f4cc.css.gz": "admin\\css\\nav_sidebar.dd925738f4cc.css.d41d8cd98f00.gz", "admin/css/responsive.css": "admin/css/responsive.d41d8cd98f00.css", "admin/css/responsive.css.gz": "admin\\css\\responsive.css.d41d8cd98f00.gz", "admin/css/responsive.eafb93ff084c.css": "admin/css/responsive.eafb93ff084c.d41d8cd98f00.css", "admin/css/responsive.eafb93ff084c.css.gz": "admin\\css\\responsive.eafb93ff084c.css.d41d8cd98f00.gz", "admin/css/responsive_rtl.7d1130848605.css": "admin/css/responsive_rtl.7d1130848605.d41d8cd98f00.css", "admin/css/responsive_rtl.7d1130848605.css.gz": "admin\\css\\responsive_rtl.7d1130848605.css.d41d8cd98f00.gz", "admin/css/responsive_rtl.css": "admin/css/responsive_rtl.d41d8cd98f00.css", "admin/css/responsive_rtl.css.gz": "admin\\css\\responsive_rtl.css.d41d8cd98f00.gz", "admin/css/rtl.aa92d763340b.css": "admin/css/rtl.aa92d763340b.d41d8cd98f00.css", "admin/css/rtl.aa92d763340b.css.gz": "admin\\css\\rtl.aa92d763340b.css.d41d8cd98f00.gz", "admin/css/rtl.css": "admin/css/rtl.d41d8cd98f00.css", "admin/css/rtl.css.gz": "admin\\css\\rtl.css.d41d8cd98f00.gz", "admin/css/widgets.8a70ea6d8850.css": "admin/css/widgets.8a70ea6d8850.d41d8cd98f00.css", "admin/css/widgets.8a70ea6d8850.css.gz": "admin\\css\\widgets.8a70ea6d8850.css.d41d8cd98f00.gz", "admin/css/widgets.css": "admin/css/widgets.d41d8cd98f00.css", "admin/css/widgets.css.gz": "admin\\css\\widgets.css.d41d8cd98f00.gz", "admin/img/calendar-icons.39b290681a8b.svg": "admin\\img\\calendar-icons.39b290681a8b.d41d8cd98f00.svg", "admin/img/calendar-icons.39b290681a8b.svg.gz": "admin\\img\\calendar-icons.39b290681a8b.svg.d41d8cd98f00.gz", "admin/img/calendar-icons.svg": "admin\\img\\calendar-icons.d41d8cd98f00.svg", "admin/img/calendar-icons.svg.gz": "admin\\img\\calendar-icons.svg.d41d8cd98f00.gz", "admin/img/icon-addlink.d519b3bab011.svg": "admin\\img\\icon-addlink.d519b3bab011.d41d8cd98f00.svg", "admin/img/icon-addlink.d519b3bab011.svg.gz": "admin\\img\\icon-addlink.d519b3bab011.svg.d41d8cd98f00.gz", "admin/img/icon-addlink.svg": "admin\\img\\icon-addlink.d41d8cd98f00.svg", "admin/img/icon-addlink.svg.gz": "admin\\img\\icon-addlink.svg.d41d8cd98f00.gz", "admin/img/icon-alert.034cc7d8a67f.svg": "admin\\img\\icon-alert.034cc7d8a67f.d41d8cd98f00.svg", "admin/img/icon-alert.034cc7d8a67f.svg.gz": "admin\\img\\icon-alert.034cc7d8a67f.svg.d41d8cd98f00.gz", "admin/img/icon-alert.svg": "admin\\img\\icon-alert.d41d8cd98f00.svg", "admin/img/icon-alert.svg.gz": "admin\\img\\icon-alert.svg.d41d8cd98f00.gz", "admin/img/icon-calendar.ac7aea671bea.svg": "admin\\img\\icon-calendar.ac7aea671bea.d41d8cd98f00.svg", "admin/img/icon-calendar.ac7aea671bea.svg.gz": "admin\\img\\icon-calendar.ac7aea671bea.svg.d41d8cd98f00.gz", "admin/img/icon-calendar.svg": "admin\\img\\icon-calendar.d41d8cd98f00.svg", "admin/img/icon-calendar.svg.gz": "admin\\img\\icon-calendar.svg.d41d8cd98f00.gz", "admin/img/icon-changelink.18d2fd706348.svg": "admin\\img\\icon-changelink.18d2fd706348.d41d8cd98f00.svg", "admin/img/icon-changelink.18d2fd706348.svg.gz": "admin\\img\\icon-changelink.18d2fd706348.svg.d41d8cd98f00.gz", "admin/img/icon-changelink.svg": "admin\\img\\icon-changelink.d41d8cd98f00.svg", "admin/img/icon-changelink.svg.gz": "admin\\img\\icon-changelink.svg.d41d8cd98f00.gz", "admin/img/icon-clock.e1d4dfac3f2b.svg": "admin\\img\\icon-clock.e1d4dfac3f2b.d41d8cd98f00.svg", "admin/img/icon-clock.e1d4dfac3f2b.svg.gz": "admin\\img\\icon-clock.e1d4dfac3f2b.svg.d41d8cd98f00.gz", "admin/img/icon-clock.svg": "admin\\img\\icon-clock.d41d8cd98f00.svg", "admin/img/icon-clock.svg.gz": "admin\\img\\icon-clock.svg.d41d8cd98f00.gz", "admin/img/icon-deletelink.564ef9dc3854.svg": "admin\\img\\icon-deletelink.564ef9dc3854.d41d8cd98f00.svg", "admin/img/icon-deletelink.564ef9dc3854.svg.gz": "admin\\img\\icon-deletelink.564ef9dc3854.svg.d41d8cd98f00.gz", "admin/img/icon-deletelink.svg": "admin\\img\\icon-deletelink.d41d8cd98f00.svg", "admin/img/icon-deletelink.svg.gz": "admin\\img\\icon-deletelink.svg.d41d8cd98f00.gz", "admin/img/icon-hidelink.8d245a995e18.svg": "admin\\img\\icon-hidelink.8d245a995e18.d41d8cd98f00.svg", "admin/img/icon-hidelink.8d245a995e18.svg.gz": "admin\\img\\icon-hidelink.8d245a995e18.svg.d41d8cd98f00.gz", "admin/img/icon-hidelink.svg": "admin\\img\\icon-hidelink.d41d8cd98f00.svg", "admin/img/icon-hidelink.svg.gz": "admin\\img\\icon-hidelink.svg.d41d8cd98f00.gz", "admin/img/icon-no.439e821418cd.svg": "admin\\img\\icon-no.439e821418cd.d41d8cd98f00.svg", "admin/img/icon-no.439e821418cd.svg.gz": "admin\\img\\icon-no.439e821418cd.svg.d41d8cd98f00.gz", "admin/img/icon-no.svg": "admin\\img\\icon-no.d41d8cd98f00.svg", "admin/img/icon-no.svg.gz": "admin\\img\\icon-no.svg.d41d8cd98f00.gz", "admin/img/icon-unknown-alt.81536e128bb6.svg": "admin\\img\\icon-unknown-alt.81536e128bb6.d41d8cd98f00.svg", "admin/img/icon-unknown-alt.81536e128bb6.svg.gz": "admin\\img\\icon-unknown-alt.81536e128bb6.svg.d41d8cd98f00.gz", "admin/img/icon-unknown-alt.svg": "admin\\img\\icon-unknown-alt.d41d8cd98f00.svg", "admin/img/icon-unknown-alt.svg.gz": "admin\\img\\icon-unknown-alt.svg.d41d8cd98f00.gz", "admin/img/icon-unknown.a18cb4398978.svg": "admin\\img\\icon-unknown.a18cb4398978.d41d8cd98f00.svg", "admin/img/icon-unknown.a18cb4398978.svg.gz": "admin\\img\\icon-unknown.a18cb4398978.svg.d41d8cd98f00.gz", "admin/img/icon-unknown.svg": "admin\\img\\icon-unknown.d41d8cd98f00.svg", "admin/img/icon-unknown.svg.gz": "admin\\img\\icon-unknown.svg.d41d8cd98f00.gz", "admin/img/icon-viewlink.41eb31f7826e.svg": "admin\\img\\icon-viewlink.41eb31f7826e.d41d8cd98f00.svg", "admin/img/icon-viewlink.41eb31f7826e.svg.gz": "admin\\img\\icon-viewlink.41eb31f7826e.svg.d41d8cd98f00.gz", "admin/img/icon-viewlink.svg": "admin\\img\\icon-viewlink.d41d8cd98f00.svg", "admin/img/icon-viewlink.svg.gz": "admin\\img\\icon-viewlink.svg.d41d8cd98f00.gz", "admin/img/icon-yes.d2f9f035226a.svg": "admin\\img\\icon-yes.d2f9f035226a.d41d8cd98f00.svg", "admin/img/icon-yes.d2f9f035226a.svg.gz": "admin\\img\\icon-yes.d2f9f035226a.svg.d41d8cd98f00.gz", "admin/img/icon-yes.svg": "admin\\img\\icon-yes.d41d8cd98f00.svg", "admin/img/icon-yes.svg.gz": "admin\\img\\icon-yes.svg.d41d8cd98f00.gz", "admin/img/inline-delete.fec1b761f254.svg": "admin\\img\\inline-delete.fec1b761f254.d41d8cd98f00.svg", "admin/img/inline-delete.fec1b761f254.svg.gz": "admin\\img\\inline-delete.fec1b761f254.svg.d41d8cd98f00.gz", "admin/img/inline-delete.svg": "admin\\img\\inline-delete.d41d8cd98f00.svg", "admin/img/inline-delete.svg.gz": "admin\\img\\inline-delete.svg.d41d8cd98f00.gz", "admin/img/LICENSE": "admin\\img\\LICENSE.d41d8cd98f00", "admin/img/LICENSE.2c54f4e1ca1c": "admin\\img\\LICENSE.d41d8cd98f00.2c54f4e1ca1c", "admin/img/LICENSE.2c54f4e1ca1c.gz": "admin\\img\\LICENSE.2c54f4e1ca1c.d41d8cd98f00.gz", "admin/img/LICENSE.gz": "admin\\img\\LICENSE.d41d8cd98f00.gz", "admin/img/README.a70711a38d87.txt": "admin\\img\\README.a70711a38d87.d41d8cd98f00.txt", "admin/img/README.a70711a38d87.txt.gz": "admin\\img\\README.a70711a38d87.txt.d41d8cd98f00.gz", "admin/img/README.txt": "admin\\img\\README.d41d8cd98f00.txt", "admin/img/README.txt.gz": "admin\\img\\README.txt.d41d8cd98f00.gz", "admin/img/search.7cf54ff789c6.svg": "admin\\img\\search.7cf54ff789c6.d41d8cd98f00.svg", "admin/img/search.7cf54ff789c6.svg.gz": "admin\\img\\search.7cf54ff789c6.svg.d41d8cd98f00.gz", "admin/img/search.svg": "admin\\img\\search.d41d8cd98f00.svg", "admin/img/search.svg.gz": "admin\\img\\search.svg.d41d8cd98f00.gz", "admin/img/selector-icons.b4555096cea2.svg": "admin\\img\\selector-icons.b4555096cea2.d41d8cd98f00.svg", "admin/img/selector-icons.b4555096cea2.svg.gz": "admin\\img\\selector-icons.b4555096cea2.svg.d41d8cd98f00.gz", "admin/img/selector-icons.svg": "admin\\img\\selector-icons.d41d8cd98f00.svg", "admin/img/selector-icons.svg.gz": "admin\\img\\selector-icons.svg.d41d8cd98f00.gz", "admin/img/sorting-icons.3a097b59f104.svg": "admin\\img\\sorting-icons.3a097b59f104.d41d8cd98f00.svg", "admin/img/sorting-icons.3a097b59f104.svg.gz": "admin\\img\\sorting-icons.3a097b59f104.svg.d41d8cd98f00.gz", "admin/img/sorting-icons.svg": "admin\\img\\sorting-icons.d41d8cd98f00.svg", "admin/img/sorting-icons.svg.gz": "admin\\img\\sorting-icons.svg.d41d8cd98f00.gz", "admin/img/tooltag-add.e59d620a9742.svg": "admin\\img\\tooltag-add.e59d620a9742.d41d8cd98f00.svg", "admin/img/tooltag-add.e59d620a9742.svg.gz": "admin\\img\\tooltag-add.e59d620a9742.svg.d41d8cd98f00.gz", "admin/img/tooltag-add.svg": "admin\\img\\tooltag-add.d41d8cd98f00.svg", "admin/img/tooltag-add.svg.gz": "admin\\img\\tooltag-add.svg.d41d8cd98f00.gz", "admin/img/tooltag-arrowright.bbfb788a849e.svg": "admin\\img\\tooltag-arrowright.bbfb788a849e.d41d8cd98f00.svg", "admin/img/tooltag-arrowright.bbfb788a849e.svg.gz": "admin\\img\\tooltag-arrowright.bbfb788a849e.svg.d41d8cd98f00.gz", "admin/img/tooltag-arrowright.svg": "admin\\img\\tooltag-arrowright.d41d8cd98f00.svg", "admin/img/tooltag-arrowright.svg.gz": "admin\\img\\tooltag-arrowright.svg.d41d8cd98f00.gz", "admin/js/actions.867b023a736d.js": "admin/js/actions.867b023a736d.b4a756f8f103.js", "admin/js/actions.867b023a736d.js.gz": "admin\\js\\actions.867b023a736d.js.d41d8cd98f00.gz", "admin/js/actions.js": "admin/js/actions.d41d8cd98f00.js", "admin/js/actions.js.gz": "admin\\js\\actions.js.d41d8cd98f00.gz", "admin/js/autocomplete.01591ab27be7.js": "admin/js/autocomplete.01591ab27be7.40ab03422935.js", "admin/js/autocomplete.01591ab27be7.js.gz": "admin\\js\\autocomplete.01591ab27be7.js.d41d8cd98f00.gz", "admin/js/autocomplete.js": "admin/js/autocomplete.d41d8cd98f00.js", "admin/js/autocomplete.js.gz": "admin\\js\\autocomplete.js.d41d8cd98f00.gz", "admin/js/calendar.d64496bbf46d.js": "admin/js/calendar.d64496bbf46d.563d27632d11.js", "admin/js/calendar.d64496bbf46d.js.gz": "admin\\js\\calendar.d64496bbf46d.js.d41d8cd98f00.gz", "admin/js/calendar.js": "admin/js/calendar.d41d8cd98f00.js", "admin/js/calendar.js.gz": "admin\\js\\calendar.js.d41d8cd98f00.gz", "admin/js/cancel.ecc4c5ca7b32.js": "admin/js/cancel.ecc4c5ca7b32.1228c7fd2a13.js", "admin/js/cancel.ecc4c5ca7b32.js.gz": "admin\\js\\cancel.ecc4c5ca7b32.js.d41d8cd98f00.gz", "admin/js/cancel.js": "admin/js/cancel.d41d8cd98f00.js", "admin/js/cancel.js.gz": "admin\\js\\cancel.js.d41d8cd98f00.gz", "admin/js/change_form.9d8ca4f96b75.js": "admin/js/change_form.9d8ca4f96b75.9b0a1db78509.js", "admin/js/change_form.9d8ca4f96b75.js.gz": "admin\\js\\change_form.9d8ca4f96b75.js.d41d8cd98f00.gz", "admin/js/change_form.js": "admin/js/change_form.d41d8cd98f00.js", "admin/js/change_form.js.gz": "admin\\js\\change_form.js.d41d8cd98f00.gz", "admin/js/collapse.f84e7410290f.js": "admin/js/collapse.f84e7410290f.614f9fae2f4d.js", "admin/js/collapse.f84e7410290f.js.gz": "admin\\js\\collapse.f84e7410290f.js.d41d8cd98f00.gz", "admin/js/collapse.js": "admin/js/collapse.d41d8cd98f00.js", "admin/js/collapse.js.gz": "admin\\js\\collapse.js.d41d8cd98f00.gz", "admin/js/core.7e257fdf56dc.js": "admin/js/core.7e257fdf56dc.fffe649db50d.js", "admin/js/core.7e257fdf56dc.js.gz": "admin\\js\\core.7e257fdf56dc.js.d41d8cd98f00.gz", "admin/js/core.js": "admin/js/core.d41d8cd98f00.js", "admin/js/core.js.gz": "admin\\js\\core.js.d41d8cd98f00.gz", "admin/js/filters.0e360b7a9f80.js": "admin/js/filters.0e360b7a9f80.4b17b1bf569b.js", "admin/js/filters.0e360b7a9f80.js.gz": "admin\\js\\filters.0e360b7a9f80.js.d41d8cd98f00.gz", "admin/js/filters.js": "admin/js/filters.d41d8cd98f00.js", "admin/js/filters.js.gz": "admin\\js\\filters.js.d41d8cd98f00.gz", "admin/js/inlines.22d4d93c00b4.js": "admin/js/inlines.22d4d93c00b4.14038f6d2f9e.js", "admin/js/inlines.22d4d93c00b4.js.gz": "admin\\js\\inlines.22d4d93c00b4.js.d41d8cd98f00.gz", "admin/js/inlines.js": "admin/js/inlines.d41d8cd98f00.js", "admin/js/inlines.js.gz": "admin\\js\\inlines.js.d41d8cd98f00.gz", "admin/js/jquery.init.b7781a0897fc.js": "admin/js/jquery.init.b7781a0897fc.e7255eadcce0.js", "admin/js/jquery.init.b7781a0897fc.js.gz": "admin\\js\\jquery.init.b7781a0897fc.js.d41d8cd98f00.gz", "admin/js/jquery.init.js": "admin/js/jquery.init.d41d8cd98f00.js", "admin/js/jquery.init.js.gz": "admin\\js\\jquery.init.js.d41d8cd98f00.gz", "admin/js/nav_sidebar.3b9190d420b1.js": "admin/js/nav_sidebar.3b9190d420b1.bb40967c30c4.js", "admin/js/nav_sidebar.3b9190d420b1.js.gz": "admin\\js\\nav_sidebar.3b9190d420b1.js.d41d8cd98f00.gz", "admin/js/nav_sidebar.js": "admin/js/nav_sidebar.d41d8cd98f00.js", "admin/js/nav_sidebar.js.gz": "admin\\js\\nav_sidebar.js.d41d8cd98f00.gz", "admin/js/popup_response.c6cc78ea5551.js": "admin/js/popup_response.c6cc78ea5551.f57b78011280.js", "admin/js/popup_response.c6cc78ea5551.js.gz": "admin\\js\\popup_response.c6cc78ea5551.js.d41d8cd98f00.gz", "admin/js/popup_response.js": "admin/js/popup_response.d41d8cd98f00.js", "admin/js/popup_response.js.gz": "admin\\js\\popup_response.js.d41d8cd98f00.gz", "admin/js/prepopulate.bd2361dfd64d.js": "admin/js/prepopulate.bd2361dfd64d.4c552da9c710.js", "admin/js/prepopulate.bd2361dfd64d.js.gz": "admin\\js\\prepopulate.bd2361dfd64d.js.d41d8cd98f00.gz", "admin/js/prepopulate.js": "admin/js/prepopulate.d41d8cd98f00.js", "admin/js/prepopulate.js.gz": "admin\\js\\prepopulate.js.d41d8cd98f00.gz", "admin/js/prepopulate_init.6cac7f3105b8.js": "admin/js/prepopulate_init.6cac7f3105b8.95ff3dc87285.js", "admin/js/prepopulate_init.6cac7f3105b8.js.gz": "admin\\js\\prepopulate_init.6cac7f3105b8.js.d41d8cd98f00.gz", "admin/js/prepopulate_init.js": "admin/js/prepopulate_init.d41d8cd98f00.js", "admin/js/prepopulate_init.js.gz": "admin\\js\\prepopulate_init.js.d41d8cd98f00.gz", "admin/js/SelectBox.7d3ce5a98007.js": "admin/js/SelectBox.7d3ce5a98007.d41d8cd98f00.js", "admin/js/SelectBox.7d3ce5a98007.js.gz": "admin\\js\\SelectBox.7d3ce5a98007.js.d41d8cd98f00.gz", "admin/js/SelectBox.js": "admin/js/SelectBox.d41d8cd98f00.js", "admin/js/SelectBox.js.gz": "admin\\js\\SelectBox.js.d41d8cd98f00.gz", "admin/js/SelectFilter2.b8cf7343ff9e.js": "admin/js/SelectFilter2.b8cf7343ff9e.d41d8cd98f00.js", "admin/js/SelectFilter2.b8cf7343ff9e.js.gz": "admin\\js\\SelectFilter2.b8cf7343ff9e.js.d41d8cd98f00.gz", "admin/js/SelectFilter2.js": "admin/js/SelectFilter2.d41d8cd98f00.js", "admin/js/SelectFilter2.js.gz": "admin\\js\\SelectFilter2.js.d41d8cd98f00.gz", "admin/js/theme.ab270f56bb9c.js": "admin/js/theme.ab270f56bb9c.d41d8cd98f00.js", "admin/js/theme.ab270f56bb9c.js.gz": "admin\\js\\theme.ab270f56bb9c.js.d41d8cd98f00.gz", "admin/js/theme.js": "admin/js/theme.d41d8cd98f00.js", "admin/js/theme.js.gz": "admin\\js\\theme.js.d41d8cd98f00.gz", "admin/js/urlify.ae970a820212.js": "admin/js/urlify.ae970a820212.d41d8cd98f00.js", "admin/js/urlify.ae970a820212.js.gz": "admin\\js\\urlify.ae970a820212.js.d41d8cd98f00.gz", "admin/js/urlify.js": "admin/js/urlify.d41d8cd98f00.js", "admin/js/urlify.js.gz": "admin\\js\\urlify.js.d41d8cd98f00.gz", "images/test plants/monstera-plant.jpg": "images\\test plants\\monstera-plant.d41d8cd98f00.jpg", "images/test plants/pexels-achim-bongard-352096.jpg": "images\\test plants\\pexels-achim-bongard-352096.d41d8cd98f00.jpg", "images/test plants/rose.jpg": "images\\test plants\\rose.d41d8cd98f00.jpg", "images/test plants/Screenshot_2024-03-11_at_17.10.16.png": "images\\test plants\\Screenshot_2024-03-11_at_17.10.16.d41d8cd98f00.png", "css/clash-display.css": "css/clash-display.90ff07048bf1.css", "css/style.css": "css/style.d759ec2e7dc6.css", "fonts/ClashDisplay-Variable.eot": "fonts\\ClashDisplay-Variable.a2eee7084f70.eot", "fonts/ClashDisplay-Variable.ttf": "fonts\\ClashDisplay-Variable.2fcd723a1a01.ttf", "fonts/ClashDisplay-Variable.woff": "fonts\\ClashDisplay-Variable.303c83362916.woff", "fonts/ClashDisplay-Variable.woff2": "fonts\\ClashDisplay-Variable.09fd55f1eaf6.woff2", "images/Alpine lady fern.jpg": "images\\Alpine lady fern.d41d8cd98f00.jpg", "images/Alpine_lady_fern.jpg": "images\\Alpine_lady_fern.d41d8cd98f00.jpg", "images/Alpine_lady_fern_1Phhruj.jpg": "images\\Alpine_lady_fern_1Phhruj.e07631494781.jpg", "images/back.jpg": "images\\back.86dccc255a80.jpg", "images/Beib arum.jpeg": "images\\Beib arum.d41d8cd98f00.jpeg", "images/Beib_arum.jpeg": "images\\Beib_arum.d41d8cd98f00.jpeg", "images/Daisy.jpeg": "images\\Daisy.d41d8cd98f00.jpeg", "images/Eastern sowbread.jpeg": "images\\Eastern sowbread.d41d8cd98f00.jpeg", "images/Eastern_sowbread.jpeg": "images\\Eastern_sowbread.d41d8cd98f00.jpeg", "images/Elephant-ears.jpg": "images\\Elephant-ears.d41d8cd98f00.jpg", "images/Elephant-ears_ypYPuLe.jpg": "images\\Elephant-ears_ypYPuLe.d41d8cd98f00.jpg", "images/English primrose.jpeg": "images\\English primrose.d41d8cd98f00.jpeg", "images/Fragrant hellebore.jpeg": "images\\Fragrant hellebore.d41d8cd98f00.jpeg", "images/Hedge fern.jpeg": "images\\Hedge fern.d41d8cd98f00.jpeg", "images/Honsh\u016b Magnolia.jpeg": "images\\Honsh\u016b Magnolia.d41d8cd98f00.jpeg", "images/Honsh\u016b_Magnolia.jpeg": "images\\Honsh\u016b_Magnolia.d41d8cd98f00.jpeg", "images/Ivy.jpeg": "images\\Ivy.d41d8cd98f00.jpeg", "images/Ivy_CWXGq4F.jpeg": "images\\Ivy_CWXGq4F.d41d8cd98f00.jpeg", "images/Ivy_V0ioM4h.jpeg": "images\\Ivy_V0ioM4h.7ddda2a6a9be.jpeg", "images/Japanese willow-leaf magnolia.jpeg": "images\\Japanese willow-leaf magnolia.d41d8cd98f00.jpeg", "images/Lenten-rose.jpeg": "images\\Lenten-rose.d41d8cd98f00.jpeg", "images/Lenten-rose_ZgspLU9.jpeg": "images\\Lenten-rose_ZgspLU9.d41d8cd98f00.jpeg", "images/Maritime pine.jpeg": "images\\Maritime pine.d41d8cd98f00.jpeg", "images/new easter sowbread.jpg": "images\\new easter sowbread.cf14298441a8.jpg", "images/new_easter_sowbread.jpg": "images\\new_easter_sowbread.cf14298441a8.jpg", "images/Primrose peerless.jpeg": "images\\Primrose peerless.d41d8cd98f00.jpeg", "images/Rhododendron.jpg": "images\\Rhododendron.d41d8cd98f00.jpg", "images/Scotch pine.jpg": "images\\Scotch pine.d41d8cd98f00.jpg", "images/Scotch_pine.jpg": "images\\Scotch_pine.d41d8cd98f00.jpg", "images/Scotch_pine_yEZP0Od.jpg": "images\\Scotch_pine_yEZP0Od.e3029a0b1c04.jpg", "images/Siberian squill.jpg": "images\\Siberian squill.d41d8cd98f00.jpg", "images/Star magnolia.jpeg": "images\\Star magnolia.d41d8cd98f00.jpeg", "images/Star_magnolia.jpeg": "images\\Star_magnolia.d41d8cd98f00.jpeg", "images/Stinking Iris.jpg": "images\\Stinking Iris.d41d8cd98f00.jpg", "images/Summer snowflake.jpeg": "images\\Summer snowflake.d41d8cd98f00.jpeg", "images/Taddiforde_Ponds_November_2011.jpg": "images\\Taddiforde_Ponds_November_2011.d5d6b4a3fc0b.jpg", "images/Tea-oil-plant.jpeg": "images\\Tea-oil-plant.d41d8cd98f00.jpeg", "images/Two-coloured Daffodil.jpeg": "images\\Two-coloured Daffodil.d41d8cd98f00.jpeg", "images/Two-coloured_Daffodil.jpeg": "images\\Two-coloured_Daffodil.d41d8cd98f00.jpeg", "images/Two-coloured_Daffodil_9LPVsRc.jpeg": "images\\Two-coloured_Daffodil_9LPVsRc.32dce8fea679.jpeg", "images/uni.jpg": "images\\uni.79311bb052f9.jpg", "js/script.js": "js/script.2ea993bbec94.js", "staticfiles.json": "staticfiles.59d554760b13.json"}, "version": "1.1", "hash": "9c73d51c3daf"}